setup.py
zlc_get_time.egg-info/PKG-INFO
zlc_get_time.egg-info/SOURCES.txt
zlc_get_time.egg-info/dependency_links.txt
zlc_get_time.egg-info/entry_points.txt
zlc_get_time.egg-info/top_level.txt
zlc_test_package/__init__.py