Metadata-Version: 1.0
Name: zlc-get-time
Version: 0.0.4
Summary: 获取任意时间/获取当前的时间戳/时间转时间戳/时间戳转时间
Home-page: https://github.com/Coxhuang/get_time
Author: ZhangLichao
Author-email: gmhesat@gmail.com
License: UNKNOWN
Platform: UNKNOWN
